streaminghub_curator/__init__.py
streaminghub_curator/__main__.py
streaminghub_curator/config.py
streaminghub_curator/typing.py
streaminghub_curator/util.py
streaminghub_curator/static/download.png
streaminghub_curator/static/favicon.ico
streaminghub_curator/static/logo.png
streaminghub_curator/static/root.png
streaminghub_curator/static/css/.DS_Store
streaminghub_curator/static/css/style.css
streaminghub_curator/static/icons/audio.png
streaminghub_curator/static/icons/code.png
streaminghub_curator/static/icons/compressed.png
streaminghub_curator/static/icons/doc.png
streaminghub_curator/static/icons/file.png
streaminghub_curator/static/icons/folder.png
streaminghub_curator/static/icons/image.png
streaminghub_curator/static/icons/numpy.png
streaminghub_curator/static/icons/pdf.png
streaminghub_curator/static/icons/txt.png
streaminghub_curator/static/icons/video.png
streaminghub_curator/static/js/metadata_editor.jsx
streaminghub_curator/templates/attributes.html
streaminghub_curator/templates/config.json
streaminghub_curator/templates/config_win.json
streaminghub_curator/templates/error.html
streaminghub_curator/templates/export.html
streaminghub_curator/templates/home.html
streaminghub_curator/templates/layout.html
streaminghub_curator/templates/login.html
streaminghub_curator/templates/streams.html
streaminghub_curator/templates/tp_dict.json
streaminghub_curator/templates/uploadsuccess.html
streaminghub_curator-0.0.1.dist-info/LICENSE
streaminghub_curator-0.0.1.dist-info/METADATA
streaminghub_curator-0.0.1.dist-info/WHEEL
streaminghub_curator-0.0.1.dist-info/top_level.txt
streaminghub_curator-0.0.1.dist-info/RECORD
