Metadata-Version: 2.1
Name: streaminghub-curator
Version: 0.0.1
Summary: A web interface to package datasets with DFDS metadata
Author-email: Yasith Jayawardana <yasith@cs.odu.edu>
License: Copyright (c) 2024 Old Dominion University
Project-URL: homepage, https://github.com/nirdslab/streaminghub/tree/master/curator
Keywords: dfds,metadata,packaging
Classifier: Programming Language :: Python :: 3
Classifier: License :: OSI Approved :: MIT License
Classifier: Operating System :: OS Independent
Requires-Python: >=3.10
License-File: LICENSE
Requires-Dist: flask
Requires-Dist: flask-session
Requires-Dist: hurry.filesize
Requires-Dist: werkzeug
Requires-Dist: pydantic
Requires-Dist: parse
Provides-Extra: dev
Requires-Dist: build ; extra == 'dev'
Requires-Dist: twine ; extra == 'dev'
Requires-Dist: bumpver ; extra == 'dev'
Requires-Dist: pip-tools ; extra == 'dev'
Requires-Dist: pytest ; extra == 'dev'
